analytic_continuation/__init__.py
analytic_continuation/continuation.py
analytic_continuation/intrinsic_curve.py
analytic_continuation/laurent.py
analytic_continuation/logging_config.py
analytic_continuation/meromorphic.py
analytic_continuation/progress.py
analytic_continuation/py.typed
analytic_continuation/space_adapter.py
analytic_continuation/types.py
analytic_continuation/schemas/__init__.py
analytic_continuation/schemas/function_contracts.json
analytic_continuation/schemas/types.json
analytic_continuation/schemas/config/pipeline_config.json
analytic_continuation/schemas/examples/spline_export.sample.json
analytic_continuation-0.1.0.dist-info/METADATA
analytic_continuation-0.1.0.dist-info/WHEEL
analytic_continuation-0.1.0.dist-info/licenses/LICENSE
analytic_continuation-0.1.0.dist-info/RECORD
