Metadata-Version: 2.4
Name: analytic-continuation
Version: 0.1.0
Summary: Coordinate transforms, Laurent series fitting, and analytic continuation pipeline utilities for complex analysis
Project-URL: Homepage, https://github.com/example/analytic-continuation
Project-URL: Documentation, https://analytic-continuation.readthedocs.io
Project-URL: Repository, https://github.com/example/analytic-continuation
Project-URL: Issues, https://github.com/example/analytic-continuation/issues
Author: Erik Goughnour
License-Expression: MIT
License-File: LICENSE
Keywords: analytic-continuation,complex-analysis,conformal-mapping,coordinate-transforms,laurent-series,meromorphic-functions
Classifier: Development Status :: 4 - Beta
Classifier: Intended Audience :: Developers
Classifier: Intended Audience :: Science/Research
Classifier: License :: OSI Approved :: MIT License
Classifier: Operating System :: OS Independent
Classifier: Programming Language :: Python :: 3
Classifier: Programming Language :: Python :: 3.9
Classifier: Programming Language :: Python :: 3.10
Classifier: Programming Language :: Python :: 3.11
Classifier: Programming Language :: Python :: 3.12
Classifier: Topic :: Scientific/Engineering :: Mathematics
Classifier: Topic :: Scientific/Engineering :: Visualization
Classifier: Typing :: Typed
Requires-Python: >=3.9
Requires-Dist: numpy>=1.20.0
Requires-Dist: pydantic>=2.0.0
Requires-Dist: scipy>=1.7.0
Provides-Extra: dev
Requires-Dist: jsonschema>=4.0.0; extra == 'dev'
Requires-Dist: pytest-cov>=4.0.0; extra == 'dev'
Requires-Dist: pytest>=7.0.0; extra == 'dev'
Requires-Dist: sphinx-autodoc-typehints>=1.20.0; extra == 'dev'
Requires-Dist: sphinx-rtd-theme>=1.0.0; extra == 'dev'
Requires-Dist: sphinx>=6.0.0; extra == 'dev'
Provides-Extra: docs
Requires-Dist: sphinx-autodoc-typehints>=1.20.0; extra == 'docs'
Requires-Dist: sphinx-rtd-theme>=1.0.0; extra == 'docs'
Requires-Dist: sphinx>=6.0.0; extra == 'docs'
Provides-Extra: validation
Requires-Dist: jsonschema>=4.0.0; extra == 'validation'
